{"title":"นักแสดงสาวเซ็กซี่ มายด์ ณภศศิ ในชุดว่ายน้ำโชว์ส่วนเว้าส่วนโค้ง มองตาไม่กระพริบ ก็เธอช่างหุ่นดีและขาวสว่างมากจริงๆ ไม่ดูก็ไม่ได้ นานๆจะเห็นเธอมาแนวนี้ คัดมาเน้นๆให้ดูจนลูกตาแทบกระเด็นเลยแล้วกัน","images":["https://xn--12c1c0afratb1edf7x.com/wp-content/uploads/2021/07/มายด์-ณภศศิ-1-768x959-1.jpg","https://xn--12c1c0afratb1edf7x.com/wp-content/uploads/2021/07/มายด์-ณภศศิ-1-768x959-1.jpg","https://xn--12c1c0afratb1edf7x.com/wp-content/uploads/2021/07/มายด์-ณภศศิ-1-768x959-1-240x300.jpg","https://xn--12c1c0afratb1edf7x.com/wp-content/uploads/2021/07/มายด์-ณภศศิ-1-768x959-1-520x649.jpg","https://xn--12c1c0afratb1edf7x.com/wp-content/uploads/2021/07/มายด์-ณภศศิ-2-768x959-1.jpg","https://xn--12c1c0afratb1edf7x.com/wp-content/uploads/2021/07/มายด์-ณภศศิ-2-768x959-1.jpg","https://xn--12c1c0afratb1edf7x.com/wp-content/uploads/2021/07/มายด์-ณภศศิ-2-768x959-1-240x300.jpg","https://xn--12c1c0afratb1edf7x.com/wp-content/uploads/2021/07/มายด์-ณภศศิ-2-768x959-1-520x649.jpg","https://xn--12c1c0afratb1edf7x.com/wp-content/uploads/2021/07/มายด์-ณภศศิ-4-768x959-1.jpg","https://xn--12c1c0afratb1edf7x.com/wp-content/uploads/2021/07/มายด์-ณภศศิ-4-768x959-1.jpg","https://xn--12c1c0afratb1edf7x.com/wp-content/uploads/2021/07/มายด์-ณภศศิ-4-768x959-1-240x300.jpg","https://xn--12c1c0afratb1edf7x.com/wp-content/uploads/2021/07/มายด์-ณภศศิ-4-768x959-1-520x649.jpg","https://xn--12c1c0afratb1edf7x.com/wp-content/uploads/2021/07/มายด์-ณภศศิ-5-768x959-1.jpg","https://xn--12c1c0afratb1edf7x.com/wp-content/uploads/2021/07/มายด์-ณภศศิ-5-768x959-1.jpg","https://xn--12c1c0afratb1edf7x.com/wp-content/uploads/2021/07/มายด์-ณภศศิ-5-768x959-1-240x300.jpg","https://xn--12c1c0afratb1edf7x.com/wp-content/uploads/2021/07/มายด์-ณภศศิ-5-768x959-1-520x649.jpg","https://xn--12c1c0afratb1edf7x.com/wp-content/uploads/2021/07/มายด์-ณภศศิ-6-768x959-1.jpg","https://xn--12c1c0afratb1edf7x.com/wp-content/uploads/2021/07/มายด์-ณภศศิ-6-768x959-1.jpg","https://xn--12c1c0afratb1edf7x.com/wp-content/uploads/2021/07/มายด์-ณภศศิ-6-768x959-1-240x300.jpg","https://xn--12c1c0afratb1edf7x.com/wp-content/uploads/2021/07/มายด์-ณภศศิ-6-768x959-1-520x649.jpg","https://xn--12c1c0afratb1edf7x.com/wp-content/uploads/2021/07/มายด์-ณภศศิ-7-768x959-1.jpg","https://xn--12c1c0afratb1edf7x.com/wp-content/uploads/2021/07/มายด์-ณภศศิ-7-768x959-1.jpg","https://xn--12c1c0afratb1edf7x.com/wp-content/uploads/2021/07/มายด์-ณภศศิ-7-768x959-1-240x300.jpg","https://xn--12c1c0afratb1edf7x.com/wp-content/uploads/2021/07/มายด์-ณภศศิ-7-768x959-1-520x649.jpg","https://xn--12c1c0afratb1edf7x.com/wp-content/uploads/2021/07/มายด์-ณภศศิ-8-768x959-1.jpg","https://xn--12c1c0afratb1edf7x.com/wp-content/uploads/2021/07/มายด์-ณภศศิ-8-768x959-1.jpg","https://xn--12c1c0afratb1edf7x.com/wp-content/uploads/2021/07/มายด์-ณภศศิ-8-768x959-1-240x300.jpg","https://xn--12c1c0afratb1edf7x.com/wp-content/uploads/2021/07/มายด์-ณภศศิ-8-768x959-1-520x649.jpg","https://xn--12c1c0afratb1edf7x.com/wp-content/uploads/2021/07/มายด์-ณภศศิ-10-768x959-1.jpg","https://xn--12c1c0afratb1edf7x.com/wp-content/uploads/2021/07/มายด์-ณภศศิ-10-768x959-1.jpg","https://xn--12c1c0afratb1edf7x.com/wp-content/uploads/2021/07/มายด์-ณภศศิ-10-768x959-1-240x300.jpg","https://xn--12c1c0afratb1edf7x.com/wp-content/uploads/2021/07/มายด์-ณภศศิ-10-768x959-1-520x649.jpg"],"excerpt":"นักแสดงสาวเซ็กซี่มายด์ณภศนักแสดงสาวเซ็กซี่ มายด์ ณภศศิ ในชุดว่ายน้ำโชว์ส่วนเว้าส่วนโค้ง มองตาไม่กระพริบ ก็เธอช่างหุ่นดีและขาวสว่างมากจริงๆ ไม่ดูก็ไม่ได้ นานๆจะเห็นเธอมาแนวนี้ คัดมาเน้นๆให้ดูจนลูกตาแทบกระเด็นเลยแล้วกัน","first_name":"100เรื่อง นักแสดงสาวเซ็กซี่ มายด์ ณภศศิ ในชุดว่ายน้ำโชว์ส่วนเว้าส่วนโค้ง มองตาไม่กระพริบ ก็เธอช่างหุ่นดีและขาวสว่างมากจริงๆ ไม่ดูก็ไม่ได้ นานๆจะเห็นเธอมาแนวนี้ คัดมาเน้นๆให้ดูจนลูกตาแทบกระเด็นเลยแล้วกัน","last_name":"PNCKDEVAPP"}